dataops_salesforce_bulk/__init__.py
dataops_salesforce_bulk/bulk_states.py
dataops_salesforce_bulk/csv_adapter.py
dataops_salesforce_bulk/dataops_salesforce_bulk.py
dataops_salesforce_bulk/util.py
dataops_salesforce_bulk-0.0.7.dist-info/LICENSE
dataops_salesforce_bulk-0.0.7.dist-info/METADATA
dataops_salesforce_bulk-0.0.7.dist-info/WHEEL
dataops_salesforce_bulk-0.0.7.dist-info/top_level.txt
dataops_salesforce_bulk-0.0.7.dist-info/RECORD
