Metadata-Version: 2.1
Name: dataops-salesforce-bulk
Version: 0.0.7
Summary: Python interface to the Salesforce.com Bulk API.
Home-page: https://github.com/puppetlabs/salesforce-bulk
Author: Scott Persinger
Author-email: scottp@heroku.com
License: MIT
Platform: UNKNOWN
Requires-Dist: six
Requires-Dist: requests (>=2.2.1)
Requires-Dist: unicodecsv (>=0.14.1)
Requires-Dist: simple-salesforce (>=0.69)
